{
	"commentStamp" : "",
	"super" : "Object",
	"category" : "TPI",
	"classinstvars" : [ ],
	"pools" : [ ],
	"classvars" : [
		"Turno"
	],
	"instvars" : [
		"ventana",
		"tamaño",
		"modoAtaqueActivado",
		"botonAtacarJ1",
		"botonAtacarJ2",
		"barcoDeAtaqueSeleccionado",
		"jugador1",
		"jugador2",
		"jugadorQueAtaca",
		"jugadorQueColoca",
		"faseCompraActiva",
		"botonListoJ1",
		"botonListoJ2",
		"labelFichasJ1",
		"labelFichasJ2",
		"botonesCompraJ1",
		"botonesCompraJ2",
		"botonesJuegoJ1",
		"botonesJuegoJ2",
		"botonRadarJ1",
		"botonRadarJ2",
		"ventanaColocacion",
		"ventanaBatalla",
		"modoRadarActivado",
		"orientacionHorizontal",
		"orientacionActual",
		"celdasPreview",
		"botonRotacionJ1",
		"botonRotacionJ2",
		"modoMoverActivado",
		"barcoEnMovimiento",
		"labelRadarJ1",
		"labelMovJ1",
		"labelRadarJ2",
		"labelMovJ2",
		"botonMovJ1",
		"botonMovJ2",
		"turnoActual",
		"jugadorActualEnTurno",
		"turnosRadarDeshabilitado",
		"generadorAleatorio"
	],
	"name" : "BatallaNaval",
	"type" : "normal"
}